mumuk-0.1.0.dist-info/METADATA
mumuk-0.1.0.dist-info/WHEEL
mumuk-0.1.0.dist-info/entry_points.txt
mumuk-0.1.0.dist-info/licenses/LICENSE
mumuk/__init__.py
mumuk-0.1.0.dist-info/RECORD
